secondmer.py
secondmer-1.0.1.dist-info/WHEEL
secondmer-1.0.1.dist-info/METADATA
secondmer-1.0.1.dist-info/RECORD
