Metadata-Version: 2.1
Name: secondmer
Version: 1.0.1
Summary: SecondMer MILLIseconds. secondmer.start(100). Now library free!
License: TPL
Author: TikOt Studio
Author-email: tikotstudio@yandex.ru
Requires-Python: >=3.0,<4.0
Classifier: License :: Other/Proprietary License
Classifier: Programming Language :: Python :: 3
Classifier: Programming Language :: Python :: 3.4
Classifier: Programming Language :: Python :: 3.5
Classifier: Programming Language :: Python :: 3.6
Classifier: Programming Language :: Python :: 3.7
Classifier: Programming Language :: Python :: 3.8
Classifier: Programming Language :: Python :: 3.9
